Workbook

Sheet Huong dan
A1: NGÂN HÀNG CÂU HỎI KIỂM TRA HIỂU BÀI — FALCULATOR FINBOX
A2: Lập ngày 23/09/2026 · dựng từ nguồn thật, không tự nghĩ ra ngộ nhận
A4: Nguyên tắc soạn | B4: Mỗi câu hỏi phải xuất phát từ một ngộ nhận hoặc quy định ĐỌC ĐƯỢC trong nguồn thật. Không có câu nào được nghĩ ra cho đủ số. Công thức không tìm thấy nguồn thì để trống — xem sheet "Phu song".
A6: Tầng bằng chứng | B6: A · Ngộ nhận có ghi chép thật (bài báo, diễn đàn, chuyên gia ghi nhận người ta hiểu sai thế nào) | B · Quy định hoặc chuẩn chuyên môn (văn bản pháp luật, biểu phí công bố, tài liệu chuẩn) — không phải ngộ nhận quan sát được, nhưng là kiến thức bắt buộc đúng.
A8: Loại nguồn | B8: trải nghiệm = người thật kể lại hoặc báo chí vụ việc | chuyên gia = phân tích viên, Damodaran, CFA, CTCK | giáo khoa = tài liệu dạy chuẩn | quy định = văn bản pháp luật, biểu phí
A10: Kiểu hiểu cần kiểm tra
B11: D1 · Đọc kết quả — con số này nói gì và KHÔNG nói gì
B12: D2 · Điều kiện áp dụng — trường hợp nào không dùng được công thức
B13: D3 · Quy ước tính toán — tham số, quy ước, thứ tự tính dễ sai
B14: D4 · Quy định thị trường VN — luật, phí, giới hạn của thị trường Việt Nam
B15: D5 · Hậu quả bằng tiền — quyết định sai thì mất bao nhiêu tiền
A17: Cách dùng | B17: Lọc cột "Kiểu hiểu" để lấy bộ câu cho từng công thức. Mỗi công thức nên chọn số câu theo tư liệu sẵn có, KHÔNG ép đủ 5 câu — xem doc đánh giá wireframe đi kèm.
A19: Cảnh báo trích dẫn | B19: Các câu trích trong cột Giải thích được lấy qua công cụ đọc trang, phần lớn là nguyên văn nhưng một số ít có thể đã bị diễn đạt lại. Trước khi in vào sản phẩm, mở lại URL nguồn kiểm chứng từng câu.

Sheet Ngan hang cau hoi
A1: Mã câu | B1: Nhóm | C1: Công thức (id) | D1: Mức | E1: Kiểu hiểu | F1: Câu hỏi | G1: A | H1: B | I1: C | J1: D | K1: Đáp án | L1: Giải thích | M1: Tầng bằng chứng | N1: Loại nguồn | O1: Bối cảnh VN | P1: Nguồn (URL)
A2: Q001 | B2: Định giá — bội số | C2: pe | D2: Cơ bản | E2: D1 · Đọc kết quả | F2: P/E của một doanh nghiệp thép là 12,5 trong khi trung bình ngành 18,0. Nhận định nào hợp lý nhất? | G2: Cổ phiếu đang rẻ hơn ngành, nên mua vào | H2: Doanh nghiệp làm ăn kém hơn trung bình ngành | I2: Chưa kết luận được — thép là ngành chu kỳ, P/E thấp thường rơi vào đỉnh lợi nhuận | J2: P/E thấp nghĩa là EPS đang âm | K2: C | L2: Với cổ phiếu chu kỳ, quan hệ đảo ngược: P/E thấp là dấu hiệu ngành đã tới đỉnh. Dẫn Peter Lynch: “Với hầu hết các cổ phiếu, tỷ lệ P/E thấp được coi là một điều tốt lành, nhưng với các cổ phiếu chu kỳ thì điều này lại ngược lại”. HPG từng có P/E 3,41 sau khi giá đã giảm 59%. | M2: A · Ngộ nhận có ghi chép | N2: trải nghiệm | O2: Có | P2: https://cafef.vn/chuyen-nguoc-doi-nhung-co-that-p-e-thap-khong-phai-la-diem-hap-dan-cua-co-phieu-hoa-phat-2022100819552941.chn
A3: Q002 | B3: Định giá — bội số | C3: pe | D3: Cơ bản | E3: D1 · Đọc kết quả | F3: GMD năm 2018 có P/E 4,42 lần ở giá 27.700 đồng. Trong 1.830 tỷ lợi nhuận có 1.350 tỷ từ bán tài sản. P/E cốt lõi xấp xỉ bao nhiêu? | G3: Vẫn 4,42 lần — lợi nhuận là lợi nhuận | H3: Khoảng 17 lần | I3: Khoảng 2 lần | J3: Không tính được nếu chưa có báo cáo kiểm toán | K3: B | L3: Loại 1.350 tỷ lợi nhuận một lần, lợi nhuận cốt lõi còn khoảng 480 tỷ, P/E cốt lõi khoảng 17 lần — gấp gần 4 lần con số hiển thị. Nguồn kết luận: “P/E cốt lõi trong tương lai của doanh nghiệp mới là yếu tố cần quan tâm”. | M3: A · Ngộ nhận có ghi chép | N3: chuyên gia | O3: Có | P3: https://azfin.vn/p-e-thap-can-than-voi-bay-gia-tri/
A4: Q003 | B4: Định giá — bội số | C4: pe | D4: Cơ bản | E4: D2 · Điều kiện áp dụng | F4: Doanh nghiệp báo lỗ, EPS bốn quý gần nhất là −1.200 đồng. App nên hiển thị P/E thế nào? | G4: P/E âm, càng âm sâu càng rẻ | H4: P/E = 0 vì không tính được | I4: Hiện “— , —” kèm cảnh báo kết quả không có ý nghĩa | J4: Lấy trị tuyệt đối của EPS rồi tính bình thường | K4: C | L4: Khi EPS âm, P/E mất ý nghĩa so sánh. Nghịch lý được ghi nhận: P/E âm sâu hơn (−100) lại hàm ý khoản lỗ NHỎ hơn so với thị giá chứ không phải tệ hơn (−10) — tức con số không đọc theo trực giác được. Đây đúng là mã cảnh báo MEANINGLESS trong WarningCode. | M4: A · Ngộ nhận có ghi chép | N4: giáo khoa | O4: Có | P4: https://24hmoney.vn/news/chi-so-pe-5-su-that-gay-soc-ma-90-nha-dau-tu-bo-qua-c30a2690593.html
A5: Q004 | B5: Định giá — bội số | C5: pe | D5: Cơ bản | E5: D2 · Điều kiện áp dụng | F5: Hai doanh nghiệp cùng ngành, A có P/E thấp hơn B 24%. Điều gì có thể giải thích chênh lệch này mà không liên quan tới việc A rẻ hơn? | G5: A có đòn bẩy nợ cao hơn | H5: A có nhiều tiền mặt hơn | I5: A trả cổ tức đều hơn | J5: A có vốn hoá lớn hơn | K5: A | L5: P/E chịu ảnh hưởng của cấu trúc vốn còn EV/EBITDA thì không. Nguồn ghi: “Higher leverage usually (but not always) results in a lower price earnings ratio, but this does not necessarily indicate a better value stock” — và dẫn cặp Greggs/Dominos cho tín hiệu ngược nhau giữa hai chỉ số. | M5: A · Ngộ nhận có ghi chép | N5: chuyên gia | O5: Không | P5: https://www.footnotesanalyst.com/relative-valuation-conflicts-ev-ebitda-versus-p-e/
A6: Q005 | B6: Định giá — bội số | C6: pe | D6: Cơ bản | E6: D2 · Điều kiện áp dụng | F6: Ngành nào sau đây P/E kém tác dụng nhất do đặc thù ghi nhận doanh thu? | G6: Ngân hàng | H6: Xây dựng | I6: Bán lẻ | J6: Điện | K6: B | L6: Ngành xây dựng ghi nhận doanh thu theo tiến độ dự án nên lợi nhuận từng kỳ không phản ánh nhịp kinh doanh thật. Nguồn cũng nêu P/E hợp lý khác nhau theo ngành — ví dụ ngân hàng 12–14 lần. | M6: A · Ngộ nhận có ghi chép | N6: giáo khoa | O6: Có | P6: https://simplize.vn/learn/chi-so-pe
A7: Q006 | B7: Định giá — bội số | C7: pb | D7: Cơ bản | E7: D1 · Đọc kết quả | F7: Một cổ phiếu ngân hàng có P/B 0,7 lần. Cách đọc nào đúng nhất? | G7: Chắc chắn rẻ vì mua tài sản dưới giá sổ sách | H7: Thị trường đang chiết khấu rủi ro chất lượng tài sản, cần soi nợ xấu | I7: Ngân hàng sắp phá sản | J7: P/B dưới 1 là lỗi dữ liệu | K7: B | L7: Với ngân hàng, giá trị sổ sách chủ yếu là dư nợ cho vay. Nguồn cảnh báo: “khi nợ xấu tăng cao, giá trị thực tế của các khoản vay này có thể thấp hơn nhiều so với con số ghi chép trên sổ sách”, và nhắc nguyên tắc “Đừng bao giờ nhầm lẫn giữa rẻ và tốt”. | M7: A · Ngộ nhận có ghi chép | N7: chuyên gia | O7: Có | P7: https://vimo.cuthongthai.vn/blog/pb-ratio-bi-mat-dinh-gia-co-phieu-ngan-hang
A8: Q007 | B8: Định giá — bội số | C8: pb | D8: Cơ bản | E8: D2 · Điều kiện áp dụng | F8: Vì sao Damodaran nói mua dưới giá trị sổ sách không đảm bảo là mua rẻ? | G8: Vì giá trị sổ sách luôn bị khai thấp | H8: Vì giá trị sổ sách là một ý kiến kế toán, không phải giá trị thanh lý | I8: Vì P/B chỉ dùng được cho công ty Mỹ | J8: Vì thị trường luôn đúng | K8: B | L8: Damodaran: “The book value is an opinion and not a fact”. Niềm tin “P/B < 1 là rẻ” dựa trên hai giả định sai: thị trường kém tin cậy hơn kế toán, và giá trị sổ sách bằng giá trị thanh lý. Doanh nghiệp ROE thấp hoặc rủi ro cao xứng đáng giao dịch dưới book value. | M8: A · Ngộ nhận có ghi chép | N8: chuyên gia | O8: Không | P8: https://pages.stern.nyu.edu/~adamodar/pdfiles/invfables/ch4new.pdf
A9: Q008 | B9: Định giá — bội số | C9: pb | D9: Cơ bản | E9: D2 · Điều kiện áp dụng | F9: Loại doanh nghiệp nào khiến P/B trông đắt một cách sai lệch? | G9: Doanh nghiệp thép | H9: Công ty phần mềm và thương hiệu mạnh | I9: Công ty bất động sản | J9: Ngân hàng | K9: B | L9: Giá trị sổ sách chỉ ghi nhận tài sản hữu hình. Nguồn: P/B “KHÔNG phù hợp với những công ty có tài sản vô hình lớn (như các công ty phần mềm)” vì thương hiệu, bằng sáng chế, uy tín không nằm trên bảng cân đối. | M9: A · Ngộ nhận có ghi chép | N9: giáo khoa | O9: Có | P9: https://simplize.vn/learn/chi-so-pb
A10: Q009 | B10: Định giá — bội số | C10: ps | D10: Cơ bản | E10: D1 · Đọc kết quả | F10: P/S của một doanh nghiệp thấp hơn hẳn đối thủ. Kết luận nào đúng? | G10: Cổ phiếu rẻ hơn | H10: Chỉ biết trả ít hơn cho mỗi đồng doanh thu, chưa biết gì về biên lợi nhuận và nợ | I10: Doanh thu đang giảm | J10: Doanh nghiệp sắp có lãi | K10: B | L10: Nguồn: “A low P/S becomes shorthand for cheap. A high P/S becomes shorthand for overpriced. Both assumptions can be completely wrong” — và “They used the number as a final answer, not a starting point”. | M10: A · Ngộ nhận có ghi chép | N10: chuyên gia | O10: Không | P10: https://medium.com/@patrick_249/price-to-sales-the-most-misused-growth-investing-metric-e5b737c49aa3
A11: Q010 | B11: Định giá — bội số | C11: ev | D11: Cơ bản | E11: D3 · Quy ước tính toán | F11: Vì sao Enterprise Value trừ đi tiền mặt? | G11: Vì tiền mặt không sinh lời | H11: Vì bên mua nhận luôn số tiền đó nên nó bù trừ vào giá phải trả | I11: Vì tiền mặt đã tính vào nợ | J11: Vì chuẩn kế toán yêu cầu | K11: B | L11: Câu hỏi này xuất hiện thật trên diễn đàn tài chính: “i just dont understand the logic of how it would be cheaper to acquire a firm with a billion cash versus a firm with no cash”. Giải thích được chấp nhận: “the buyer would get the target company's cash as part of the deal, effectively lowering the price” — như trả 5 đô để nhận tờ 5 đô. | M11: A · Ngộ nhận có ghi chép | N11: trải nghiệm | O11: Không | P11: https://www.wallstreetoasis.com/forum/off-topic/why-subtract-cash-when-we-calculate-enterprise-value
A12: Q011 | B12: Định giá — bội số | C12: ev | D12: Cơ bản | E12: D3 · Quy ước tính toán | F12: Bội số nào sau đây là ghép sai tử số với mẫu số? | G12: P/E | H12: EV/EBITDA | I12: P/EBITDA | J12: P/B | K12: C | L12: Tử số vốn chủ (giá, vốn hoá) phải đi với mẫu số vốn chủ; mẫu số toàn doanh nghiệp (EBITDA, doanh thu) phải đi với EV. Damodaran gọi thẳng: “Price to EBITDA is an inconsistent abomination and Price to Sales is almost as badly constructed”. | M12: A · Ngộ nhận có ghi chép | N12: chuyên gia | O12: Không | P12: https://aswathdamodaran.blogspot.com/2020/04/a-viral-market-update-vii-mayhem-with.html
... A207: Q206 | B207: Vay nợ, tiết kiệm & DCA | C207: gia-von-trung-binh-dca | D207: Cơ bản | E207: D3 · Quy ước tính toán | F207: Phần lớn tranh luận “DCA có tốt không” thực ra đang nói về tình huống nào? | G207: Đầu tư đều đặn từ thu nhập hằng tháng | H207: Rải một khoản tiền lớn bất ngờ (thừa kế, tiền bảo hiểm) | I207: Mua bình quân giá xuống | J207: Đầu tư vào quỹ chỉ số | K207: B | L207: Nguồn: “The confusion occurs where the term dollar cost averaging is incorrectly used to describe a different investment strategy... where the investor invests a windfall gain such as an insurance payout or inheritance” — và “this is actually a rare event for most investors”. Hai chiến lược khác nhau nên kết luận không áp dụng chung. | M207: A · Ngộ nhận có ghi chép | N207: giáo khoa | O207: Không | P207: https://en.wikipedia.org/wiki/Dollar_cost_averaging

Sheet Phu song
A1: Nhóm | B1: Công thức (id) | C1: Mức | D1: Số câu | E1: Tình trạng
A2: Chỉ số doanh nghiệp | B2: bien-loi-nhuan-gop | C2: Cơ bản | D2: =COUNTIF('Ngan hang cau hoi'!$C$2:$C$207,B2) -> 2 | E2: Đủ dùng
A3: Chỉ số doanh nghiệp | B3: bien-loi-nhuan-rong | C3: Cơ bản | D3: =COUNTIF('Ngan hang cau hoi'!$C$2:$C$207,B3) -> 2 | E3: Đủ dùng
A4: Chỉ số doanh nghiệp | B4: bvps | C4: Cơ bản | D4: =COUNTIF('Ngan hang cau hoi'!$C$2:$C$207,B4) -> 2 | E4: Đủ dùng
A5: Chỉ số doanh nghiệp | B5: diem-hoa-von | C5: Nâng cao | D5: =COUNTIF('Ngan hang cau hoi'!$C$2:$C$207,B5) -> 1 | E5: Tư liệu mỏng, 1 câu
A6: Chỉ số doanh nghiệp | B6: don-bay-tong-hop | C6: Nâng cao | D6: =COUNTIF('Ngan hang cau hoi'!$C$2:$C$207,B6) -> 1 | E6: Tư liệu mỏng, 1 câu
A7: Chỉ số doanh nghiệp | B7: eps-co-ban | C7: Cơ bản | D7: =COUNTIF('Ngan hang cau hoi'!$C$2:$C$207,B7) -> 4 | E7: Đủ dùng
A8: Chỉ số doanh nghiệp | B8: no-tren-von-chu | C8: Cơ bản | D8: =COUNTIF('Ngan hang cau hoi'!$C$2:$C$207,B8) -> 1 | E8: Tư liệu mỏng, 1 câu
A9: Chỉ số doanh nghiệp | B9: roa | C9: Cơ bản | D9: =COUNTIF('Ngan hang cau hoi'!$C$2:$C$207,B9) -> 2 | E9: Đủ dùng
A10: Chỉ số doanh nghiệp | B10: roe | C10: Cơ bản | D10: =COUNTIF('Ngan hang cau hoi'!$C$2:$C$207,B10) -> 3 | E10: Đủ dùng
A11: Chỉ số doanh nghiệp | B11: thanh-toan-hien-hanh | C11: Cơ bản | D11: =COUNTIF('Ngan hang cau hoi'!$C$2:$C$207,B11) -> 1 | E11: Tư liệu mỏng, 1 câu
A12: Chỉ số doanh nghiệp | B12: thanh-toan-nhanh | C12: Cơ bản | D12: =COUNTIF('Ngan hang cau hoi'!$C$2:$C$207,B12) -> 1 | E12: Tư liệu mỏng, 1 câu
A13: Chỉ số doanh nghiệp | B13: ty-le-chi-tra-co-tuc | C13: Cơ bản | D13: =COUNTIF('Ngan hang cau hoi'!$C$2:$C$207,B13) -> 2 | E13: Đủ dùng
... A112: Định giá — bội số | B112: von-hoa-thi-truong | C112: Cơ bản | D112: =COUNTIF('Ngan hang cau hoi'!$C$2:$C$207,B112) -> 2 | E112: Đủ dùng

Sheet Nguon
A1: URL | B1: Loại nguồn | C1: Bối cảnh VN | D1: Số câu dùng
A2: https://www.phs.vn/san-pham-dich-vu/quy-dinh-ve-hdtl-chi-so-vn-30/22 | B2: quy định | C2: Có | D2: =COUNTIF('Ngan hang cau hoi'!$P$2:$P$207,A2) -> 4
A3: https://chartschool.stockcharts.com/table-of-contents/technical-indicators-and-overlays/technical-overlays/moving-averages-simple-and-exponential | B3: giáo khoa | C3: Không | D3: =COUNTIF('Ngan hang cau hoi'!$P$2:$P$207,A3) -> 3
A4: https://tinnhanhchungkhoan.vn/chung-khoan/chay-tai-khoan-trong-phien-dao-han-chung-khoan-phai-sinh-328263.html | B4: trải nghiệm | C4: Có | D4: =COUNTIF('Ngan hang cau hoi'!$P$2:$P$207,A4) -> 3
A5: https://vneconomy.vn/chung-khoan-phai-sinh-truoc-gio-g-4-con-ac-mong-margin-call.htm | B5: giáo khoa | C5: Có | D5: =COUNTIF('Ngan hang cau hoi'!$P$2:$P$207,A5) -> 3
A6: https://aswathdamodaran.blogspot.com/2016/05/dcf-myth-31-margin-of-safety-tool-for.html | B6: chuyên gia | C6: Không | D6: =COUNTIF('Ngan hang cau hoi'!$P$2:$P$207,A6) -> 2
A7: https://aswathdamodaran.blogspot.com/2022/10/earnings-and-cash-flows-primer-on-free.html | B7: chuyên gia | C7: Không | D7: =COUNTIF('Ngan hang cau hoi'!$P$2:$P$207,A7) -> 2
A8: https://aswathdamodaran.substack.com/p/myth-53-growth-is-good-more-growth-16-11-30 | B8: chuyên gia | C8: Không | D8: =COUNTIF('Ngan hang cau hoi'!$P$2:$P$207,A8) -> 2
A9: https://chartschool.stockcharts.com/table-of-contents/technical-indicators-and-overlays/technical-indicators/average-true-range-atr | B9: giáo khoa | C9: Không | D9: =COUNTIF('Ngan hang cau hoi'!$P$2:$P$207,A9) -> 2
A10: https://chartschool.stockcharts.com/table-of-contents/technical-indicators-and-overlays/technical-indicators/macd-moving-average-convergence-divergence-oscillator | B10: giáo khoa | C10: Không | D10: =COUNTIF('Ngan hang cau hoi'!$P$2:$P$207,A10) -> 2
A11: https://chartschool.stockcharts.com/table-of-contents/technical-indicators-and-overlays/technical-indicators/rate-of-change-roc | B11: giáo khoa | C11: Không | D11: =COUNTIF('Ngan hang cau hoi'!$P$2:$P$207,A11) -> 2
A12: https://chartschool.stockcharts.com/table-of-contents/technical-indicators-and-overlays/technical-indicators/relative-strength-index-rsi | B12: giáo khoa | C12: Không | D12: =COUNTIF('Ngan hang cau hoi'!$P$2:$P$207,A12) -> 2
A13: https://cophieux.com/chi-so-roe/ | B13: chuyên gia | C13: Có | D13: =COUNTIF('Ngan hang cau hoi'!$P$2:$P$207,A13) -> 2
... A178: https://www.wallstreetoasis.com/forum/off-topic/why-subtract-cash-when-we-calculate-enterprise-value | B178: trải nghiệm | C178: Không | D178: =COUNTIF('Ngan hang cau hoi'!$P$2:$P$207,A178) -> 1
